[{"symbol_id": 1, "time": 1566575820, "open": 1.10687, "close": 1.10686, "high": 1.10691, "low": 1.10682, "asset": "EURUSD"}, {"symbol_id": 1, "time": 1566575880, "open": 1.10686, "close": 1.10697, "high": 1.10698, "low": 1.10683, "asset": "EURUSD"}, {"symbol_id": 1, "time": 1566575940, "open": 1.10697, "close": 1.10666, "high": 1.10704, "low": 1.10659, "asset": "EURUSD"}, {"symbol_id": 1, "time": 1566576000, "open": 1.10665, "close": 1.10682, "high": 1.10684, "low": 1.10591, "asset": "EURUSD"}, {"symbol_id": 1, "time": 1566576060, "open": 1.10679, "close": 1.10758, "high": 1.10775, "low": 1.10667, "asset": "EURUSD"}, {"symbol_id": 1, "time": 1566576120, "open": 1.10759, "close": 1.10771, "high": 1.10777, "low": 1.10726, "asset": "EURUSD"}, {"symbol_id": 1, "time": 1566576180, "open": 1.10769, "close": 1.10817, "high": 1.10826, "low": 1.10763, "asset": "EURUSD"}, {"symbol_id": 1, "time": 1566576240, "open": 1.10816, "close": 1.10776, "high": 1.10828, "low": 1.10776, "asset": "EURUSD"}, {"symbol_id": 1, "time": 1566576300, "open": 1.10778, "close": 1.10792, "high": 1.10793, "low": 1.10763, "asset": "EURUSD"}, {"symbol_id": 1, "time": 1566576360, "open": 1.10796, "close": 1.10779, "high": 1.10809, "low": 1.10753, "asset": "EURUSD"}, {"symbol_id": 1, "time": 1566576420, "open": 1.10785, "close": 1.10801, "high": 1.10815, "low": 1.10781, "asset": "EURUSD"}, {"symbol_id": 1, "time": 1566576480, "open": 1.10799, "close": 1.10776, "high": 1.10806, "low": 1.10774, "asset": "EURUSD"}, {"symbol_id": 1, "time": 1566576540, "open": 1.10776, "close": 1.10741, "high": 1.10776, "low": 1.10729, "asset": "EURUSD"}, {"symbol_id": 1, "time": 1566576600, "open": 1.10741, "close": 1.1078, "high": 1.1078, "low": 1.10737, "asset": "EURUSD"}, {"symbol_id": 1, "time": 1566576660, "open": 1.1078, "close": 1.10801, "high": 1.10809, "low": 1.10779, "asset": "EURUSD"}, {"symbol_id": 1, "time": 1566576720, "open": 1.10802, "close": 1.10795, "high": 1.10808, "low": 1.10792, "asset": "EURUSD"}, {"symbol_id": 1, "time": 1566576780, "open": 1.10795, "close": 1.10762, "high": 1.10804, "low": 1.10757, "asset": "EURUSD"}, {"symbol_id": 1, "time": 1566576840, "open": 1.10761, "close": 1.10762, "high": 1.10776, "low": 1.1076, "asset": "EURUSD"}, {"symbol_id": 1, "time": 1566576900, "open": 1.10762, "close": 1.10749, "high": 1.10768, "low": 1.10745, "asset": "EURUSD"}, {"symbol_id": 1, "time": 1566576960, "open": 1.10749, "close": 1.10736, "high": 1.10751, "low": 1.10735, "asset": "EURUSD"}, {"symbol_id": 1, "time": 1566577020, "open": 1.10736, "close": 1.10722, "high": 1.10739, "low": 1.1072, "asset": "EURUSD"}, {"symbol_id": 1, "time": 1566577080, "open": 1.10722, "close": 1.10714, "high": 1.10723, "low": 1.10704, "asset": "EURUSD"}, {"symbol_id": 1, "time": 1566577140, "open": 1.10714, "close": 1.10728, "high": 1.10738, "low": 1.10714, "asset": "EURUSD"}, {"symbol_id": 1, "time": 1566577200, "open": 1.10733, "close": 1.10742, "high": 1.10743, "low": 1.10727, "asset": "EURUSD"}, {"symbol_id": 1, "time": 1566577260, "open": 1.10743, "close": 1.10733, "high": 1.10764, "low": 1.10731, "asset": "EURUSD"}, {"symbol_id": 1, "time": 1566577320, "open": 1.10733, "close": 1.10748, "high": 1.10752, "low": 1.1072, "asset": "EURUSD"}, {"symbol_id": 1, "time": 1566577380, "open": 1.10748, "close": 1.10732, "high": 1.10748, "low": 1.1073, "asset": "EURUSD"}, {"symbol_id": 1, "time": 1566577440, "open": 1.10732, "close": 1.10744, "high": 1.10744, "low": 1.10727, "asset": "EURUSD"}, {"symbol_id": 1, "time": 1566577500, "open": 1.10744, "close": 1.1079, "high": 1.1079, "low": 1.10742, "asset": "EURUSD"}, {"symbol_id": 1, "time": 1566577560, "open": 1.1079, "close": 1.10815, "high": 1.10815, "low": 1.10785, "asset": "EURUSD"}, {"symbol_id": 1, "time": 1566577620, "open": 1.10814, "close": 1.10802, "high": 1.1082, "low": 1.10793, "asset": "EURUSD"}, {"symbol_id": 1, "time": 1566577680, "open": 1.10804, "close": 1.10794, "high": 1.1081, "low": 1.10791, "asset": "EURUSD"}, {"symbol_id": 1, "time": 1566577740, "open": 1.10796, "close": 1.10795, "high": 1.10798, "low": 1.10774, "asset": "EURUSD"}, {"symbol_id": 1, "time": 1566577800, "open": 1.10794, "close": 1.10782, "high": 1.10797, "low": 1.10774, "asset": "EURUSD"}, {"symbol_id": 1, "time": 1566577860, "open": 1.10781, "close": 1.10826, "high": 1.10827, "low": 1.10779, "asset": "EURUSD"}, {"symbol_id": 1, "time": 1566577920, "open": 1.10827, "close": 1.1084, "high": 1.10849, "low": 1.10822, "asset": "EURUSD"}, {"symbol_id": 1, "time": 1566577980, "open": 1.10838, "close": 1.10828, "high": 1.10839, "low": 1.10813, "asset": "EURUSD"}, {"symbol_id": 1, "time": 1566578040, "open": 1.10829, "close": 1.10812, "high": 1.1083, "low": 1.10802, "asset": "EURUSD"}, {"symbol_id": 1, "time": 1566578100, "open": 1.10812, "close": 1.10805, "high": 1.10829, "low": 1.10804, "asset": "EURUSD"}, {"symbol_id": 1, "time": 1566578160, "open": 1.10805, "close": 1.10802, "high": 1.10813, "low": 1.10797, "asset": "EURUSD"}, {"symbol_id": 1, "time": 1566578220, "open": 1.10802, "close": 1.10801, "high": 1.10815, "low": 1.10797, "asset": "EURUSD"}, {"symbol_id": 1, "time": 1566578280, "open": 1.10801, "close": 1.10791, "high": 1.10811, "low": 1.10791, "asset": "EURUSD"}, {"symbol_id": 1, "time": 1566578340, "open": 1.10791, "close": 1.1077, "high": 1.10794, "low": 1.1077, "asset": "EURUSD"}, {"symbol_id": 1, "time": 1566578400, "open": 1.1077, "close": 1.10757, "high": 1.10773, "low": 1.10751, "asset": "EURUSD"}, {"symbol_id": 1, "time": 1566578460, "open": 1.10757, "close": 1.10793, "high": 1.10799, "low": 1.10756, "asset": "EURUSD"}, {"symbol_id": 1, "time": 1566578520, "open": 1.10792, "close": 1.10794, "high": 1.10818, "low": 1.10792, "asset": "EURUSD"}, {"symbol_id": 1, "time": 1566578580, "open": 1.10794, "close": 1.10848, "high": 1.1085, "low": 1.10794, "asset": "EURUSD"}, {"symbol_id": 1, "time": 1566578640, "open": 1.10848, "close": 1.10878, "high": 1.10882, "low": 1.10844, "asset": "EURUSD"}, {"symbol_id": 1, "time": 1566578700, "open": 1.10878, "close": 1.10897, "high": 1.10899, "low": 1.10858, "asset": "EURUSD"}, {"symbol_id": 1, "time": 1566578760, "open": 1.10897, "close": 1.10912, "high": 1.10928, "low": 1.10897, "asset": "EURUSD"}, {"symbol_id": 1, "time": 1566578820, "open": 1.10912, "close": 1.10982, "high": 1.10982, "low": 1.10901, "asset": "EURUSD"}, {"symbol_id": 1, "time": 1566578880, "open": 1.10982, "close": 1.1102, "high": 1.11025, "low": 1.10966, "asset": "EURUSD"}, {"symbol_id": 1, "time": 1566578940, "open": 1.1102, "close": 1.11035, "high": 1.11061, "low": 1.11019, "asset": "EURUSD"}, {"symbol_id": 1, "time": 1566579000, "open": 1.11033, "close": 1.1102, "high": 1.11033, "low": 1.11002, "asset": "EURUSD"}, {"symbol_id": 1, "time": 1566579060, "open": 1.1102, "close": 1.11089, "high": 1.11089, "low": 1.1102, "asset": "EURUSD"}, {"symbol_id": 1, "time": 1566579120, "open": 1.11096, "close": 1.11118, "high": 1.11147, "low": 1.11088, "asset": "EURUSD"}, {"symbol_id": 1, "time": 1566579180, "open": 1.11119, "close": 1.11081, "high": 1.11143, "low": 1.11052, "asset": "EURUSD"}, {"symbol_id": 1, "time": 1566579240, "open": 1.11081, "close": 1.11079, "high": 1.11098, "low": 1.11068, "asset": "EURUSD"}, {"symbol_id": 1, "time": 1566579300, "open": 1.11078, "close": 1.111, "high": 1.1112, "low": 1.11054, "asset": "EURUSD"}, {"symbol_id": 1, "time": 1566579360, "open": 1.11101, "close": 1.1108, "high": 1.11101, "low": 1.11057, "asset": "EURUSD"}, {"symbol_id": 1, "time": 1566579420, "open": 1.11081, "close": 1.11041, "high": 1.11082, "low": 1.1104, "asset": "EURUSD"}, {"symbol_id": 1, "time": 1566579480, "open": 1.11042, "close": 1.11065, "high": 1.11072, "low": 1.11042, "asset": "EURUSD"}, {"symbol_id": 1, "time": 1566579540, "open": 1.11064, "close": 1.11102, "high": 1.11137, "low": 1.11064, "asset": "EURUSD"}, {"symbol_id": 1, "time": 1566579600, "open": 1.11098, "close": 1.11108, "high": 1.11136, "low": 1.11094, "asset": "EURUSD"}, {"symbol_id": 1, "time": 1566579660, "open": 1.11108, "close": 1.1111, "high": 1.11133, "low": 1.11068, "asset": "EURUSD"}, {"symbol_id": 1, "time": 1566579720, "open": 1.1111, "close": 1.11093, "high": 1.11111, "low": 1.1104, "asset": "EURUSD"}, {"symbol_id": 1, "time": 1566579780, "open": 1.11093, "close": 1.11089, "high": 1.11101, "low": 1.11051, "asset": "EURUSD"}, {"symbol_id": 1, "time": 1566579840, "open": 1.11089, "close": 1.11171, "high": 1.11177, "low": 1.11081, "asset": "EURUSD"}, {"symbol_id": 1, "time": 1566579900, "open": 1.11171, "close": 1.11246, "high": 1.11262, "low": 1.11171, "asset": "EURUSD"}, {"symbol_id": 1, "time": 1566579960, "open": 1.11246, "close": 1.11192, "high": 1.11246, "low": 1.11165, "asset": "EURUSD"}, {"symbol_id": 1, "time": 1566580020, "open": 1.11192, "close": 1.11217, "high": 1.11237, "low": 1.11173, "asset": "EURUSD"}, {"symbol_id": 1, "time": 1566580080, "open": 1.11217, "close": 1.11217, "high": 1.11236, "low": 1.11201, "asset": "EURUSD"}, {"symbol_id": 1, "time": 1566580140, "open": 1.11217, "close": 1.11231, "high": 1.11236, "low": 1.11211, "asset": "EURUSD"}, {"symbol_id": 1, "time": 1566580200, "open": 1.11231, "close": 1.11256, "high": 1.11289, "low": 1.11231, "asset": "EURUSD"}, {"symbol_id": 1, "time": 1566580260, "open": 1.11258, "close": 1.11253, "high": 1.11288, "low": 1.11241, "asset": "EURUSD"}, {"symbol_id": 1, "time": 1566580320, "open": 1.11253, "close": 1.11272, "high": 1.11282, "low": 1.11235, "asset": "EURUSD"}, {"symbol_id": 1, "time": 1566580380, "open": 1.11272, "close": 1.11289, "high": 1.11295, "low": 1.11267, "asset": "EURUSD"}, {"symbol_id": 1, "time": 1566580440, "open": 1.11287, "close": 1.11289, "high": 1.11317, "low": 1.11263, "asset": "EURUSD"}, {"symbol_id": 1, "time": 1566580500, "open": 1.11289, "close": 1.11317, "high": 1.11345, "low": 1.11285, "asset": "EURUSD"}, {"symbol_id": 1, "time": 1566580560, "open": 1.11317, "close": 1.11249, "high": 1.11319, "low": 1.11249, "asset": "EURUSD"}, {"symbol_id": 1, "time": 1566580620, "open": 1.11249, "close": 1.1122, "high": 1.1125, "low": 1.1122, "asset": "EURUSD"}, {"symbol_id": 1, "time": 1566580680, "open": 1.11222, "close": 1.11196, "high": 1.11232, "low": 1.11189, "asset": "EURUSD"}, {"symbol_id": 1, "time": 1566580740, "open": 1.11195, "close": 1.11208, "high": 1.11214, "low": 1.11195, "asset": "EURUSD"}, {"symbol_id": 1, "time": 1566580800, "open": 1.11205, "close": 1.11273, "high": 1.11278, "low": 1.11202, "asset": "EURUSD"}, {"symbol_id": 1, "time": 1566580860, "open": 1.11273, "close": 1.11301, "high": 1.11307, "low": 1.11264, "asset": "EURUSD"}, {"symbol_id": 1, "time": 1566580920, "open": 1.11302, "close": 1.11295, "high": 1.11321, "low": 1.11291, "asset": "EURUSD"}, {"symbol_id": 1, "time": 1566580980, "open": 1.11292, "close": 1.11298, "high": 1.11299, "low": 1.11268, "asset": "EURUSD"}, {"symbol_id": 1, "time": 1566581040, "open": 1.11301, "close": 1.11328, "high": 1.11336, "low": 1.11299, "asset": "EURUSD"}, {"symbol_id": 1, "time": 1566581100, "open": 1.11332, "close": 1.11382, "high": 1.11389, "low": 1.11332, "asset": "EURUSD"}, {"symbol_id": 1, "time": 1566581160, "open": 1.11382, "close": 1.11387, "high": 1.11392, "low": 1.11364, "asset": "EURUSD"}, {"symbol_id": 1, "time": 1566581220, "open": 1.11389, "close": 1.11393, "high": 1.11401, "low": 1.11373, "asset": "EURUSD"}, {"symbol_id": 1, "time": 1566581280, "open": 1.11393, "close": 1.11395, "high": 1.11398, "low": 1.11372, "asset": "EURUSD"}, {"symbol_id": 1, "time": 1566581340, "open": 1.11395, "close": 1.11395, "high": 1.11427, "low": 1.11385, "asset": "EURUSD"}, {"symbol_id": 1, "time": 1566581400, "open": 1.11395, "close": 1.1144, "high": 1.11449, "low": 1.11388, "asset": "EURUSD"}, {"symbol_id": 1, "time": 1566581460, "open": 1.1144, "close": 1.11439, "high": 1.11465, "low": 1.11438, "asset": "EURUSD"}, {"symbol_id": 1, "time": 1566581520, "open": 1.11439, "close": 1.11457, "high": 1.11462, "low": 1.11423, "asset": "EURUSD"}, {"symbol_id": 1, "time": 1566581580, "open": 1.11456, "close": 1.11432, "high": 1.1146, "low": 1.1141, "asset": "EURUSD"}, {"symbol_id": 1, "time": 1566581640, "open": 1.1143, "close": 1.11387, "high": 1.11451, "low": 1.11375, "asset": "EURUSD"}, {"symbol_id": 1, "time": 1566581700, "open": 1.11388, "close": 1.11403, "high": 1.1141, "low": 1.11372, "asset": "EURUSD"}, {"symbol_id": 1, "time": 1566581760, "open": 1.11403, "close": 1.11443, "high": 1.1145, "low": 1.11403, "asset": "EURUSD"}, {"symbol_id": 1, "time": 1566581820, "open": 1.11444, "close": 1.11426, "high": 1.11445, "low": 1.1142, "asset": "EURUSD"}, {"symbol_id": 1, "time": 1566581880, "open": 1.11426, "close": 1.11418, "high": 1.11449, "low": 1.11416, "asset": "EURUSD"}, {"symbol_id": 1, "time": 1566581940, "open": 1.11418, "close": 1.11427, "high": 1.11449, "low": 1.11416, "asset": "EURUSD"}, {"symbol_id": 1, "time": 1566582000, "open": 1.11427, "close": 1.11436, "high": 1.11468, "low": 1.11423, "asset": "EURUSD"}, {"symbol_id": 1, "time": 1566582060, "open": 1.11436, "close": 1.11436, "high": 1.11447, "low": 1.11425, "asset": "EURUSD"}, {"symbol_id": 1, "time": 1566582120, "open": 1.11437, "close": 1.11417, "high": 1.11437, "low": 1.11416, "asset": "EURUSD"}, {"symbol_id": 1, "time": 1566582180, "open": 1.11415, "close": 1.11408, "high": 1.11417, "low": 1.11394, "asset": "EURUSD"}, {"symbol_id": 1, "time": 1566582240, "open": 1.11408, "close": 1.11393, "high": 1.11418, "low": 1.11393, "asset": "EURUSD"}, {"symbol_id": 1, "time": 1566582300, "open": 1.11392, "close": 1.1141, "high": 1.11417, "low": 1.11371, "asset": "EURUSD"}, {"symbol_id": 1, "time": 1566582360, "open": 1.1141, "close": 1.11386, "high": 1.1141, "low": 1.11383, "asset": "EURUSD"}, {"symbol_id": 1, "time": 1566582420, "open": 1.11386, "close": 1.11376, "high": 1.11386, "low": 1.1137, "asset": "EURUSD"}, {"symbol_id": 1, "time": 1566582480, "open": 1.11375, "close": 1.11361, "high": 1.11385, "low": 1.11359, "asset": "EURUSD"}, {"symbol_id": 1, "time": 1566582540, "open": 1.11361, "close": 1.11352, "high": 1.11374, "low": 1.11351, "asset": "EURUSD"}, {"symbol_id": 1, "time": 1566582600, "open": 1.11353, "close": 1.1133, "high": 1.11357, "low": 1.1133, "asset": "EURUSD"}, {"symbol_id": 1, "time": 1566582660, "open": 1.11329, "close": 1.11344, "high": 1.11347, "low": 1.11329, "asset": "EURUSD"}, {"symbol_id": 1, "time": 1566582720, "open": 1.11344, "close": 1.11368, "high": 1.11368, "low": 1.1133, "asset": "EURUSD"}, {"symbol_id": 1, "time": 1566582780, "open": 1.11369, "close": 1.11372, "high": 1.11382, "low": 1.11367, "asset": "EURUSD"}, {"symbol_id": 1, "time": 1566582840, "open": 1.11375, "close": 1.11408, "high": 1.11411, "low": 1.11375, "asset": "EURUSD"}, {"symbol_id": 1, "time": 1566582900, "open": 1.11408, "close": 1.11432, "high": 1.11432, "low": 1.11397, "asset": "EURUSD"}, {"symbol_id": 1, "time": 1566582960, "open": 1.11433, "close": 1.1146, "high": 1.11471, "low": 1.11428, "asset": "EURUSD"}, {"symbol_id": 1, "time": 1566583020, "open": 1.11462, "close": 1.11458, "high": 1.11462, "low": 1.11434, "asset": "EURUSD"}, {"symbol_id": 1, "time": 1566583080, "open": 1.11458, "close": 1.1145, "high": 1.11458, "low": 1.11438, "asset": "EURUSD"}, {"symbol_id": 1, "time": 1566583140, "open": 1.1145, "close": 1.11472, "high": 1.11475, "low": 1.11446, "asset": "EURUSD"}, {"symbol_id": 1, "time": 1566583200, "open": 1.11472, "close": 1.11351, "high": 1.11472, "low": 1.11351, "asset": "EURUSD"}, {"symbol_id": 1, "time": 1566583260, "open": 1.11351, "close": 1.11343, "high": 1.11391, "low": 1.11342, "asset": "EURUSD"}, {"symbol_id": 1, "time": 1566583320, "open": 1.11343, "close": 1.11353, "high": 1.11362, "low": 1.1134, "asset": "EURUSD"}, {"symbol_id": 1, "time": 1566583380, "open": 1.11353, "close": 1.11368, "high": 1.11369, "low": 1.11347, "asset": "EURUSD"}, {"symbol_id": 1, "time": 1566583440, "open": 1.11368, "close": 1.11372, "high": 1.11385, "low": 1.11359, "asset": "EURUSD"}, {"symbol_id": 1, "time": 1566583500, "open": 1.11372, "close": 1.11372, "high": 1.11384, "low": 1.1136, "asset": "EURUSD"}, {"symbol_id": 1, "time": 1566583560, "open": 1.11372, "close": 1.11335, "high": 1.11386, "low": 1.11333, "asset": "EURUSD"}, {"symbol_id": 1, "time": 1566583620, "open": 1.11335, "close": 1.1135, "high": 1.1135, "low": 1.11325, "asset": "EURUSD"}, {"symbol_id": 1, "time": 1566583680, "open": 1.11351, "close": 1.11342, "high": 1.11353, "low": 1.11333, "asset": "EURUSD"}, {"symbol_id": 1, "time": 1566583740, "open": 1.11342, "close": 1.11303, "high": 1.11342, "low": 1.113, "asset": "EURUSD"}, {"symbol_id": 1, "time": 1566583800, "open": 1.11304, "close": 1.113, "high": 1.1133, "low": 1.11298, "asset": "EURUSD"}, {"symbol_id": 1, "time": 1566583860, "open": 1.113, "close": 1.11322, "high": 1.11324, "low": 1.113, "asset": "EURUSD"}, {"symbol_id": 1, "time": 1566583920, "open": 1.11323, "close": 1.1134, "high": 1.11341, "low": 1.11322, "asset": "EURUSD"}, {"symbol_id": 1, "time": 1566583980, "open": 1.11341, "close": 1.11313, "high": 1.11351, "low": 1.11313, "asset": "EURUSD"}, {"symbol_id": 1, "time": 1566584040, "open": 1.11313, "close": 1.11292, "high": 1.11336, "low": 1.11292, "asset": "EURUSD"}, {"symbol_id": 1, "time": 1566584100, "open": 1.11292, "close": 1.11301, "high": 1.11302, "low": 1.11282, "asset": "EURUSD"}, {"symbol_id": 1, "time": 1566584160, "open": 1.113, "close": 1.11291, "high": 1.11309, "low": 1.11289, "asset": "EURUSD"}, {"symbol_id": 1, "time": 1566584220, "open": 1.11292, "close": 1.11305, "high": 1.11308, "low": 1.11292, "asset": "EURUSD"}, {"symbol_id": 1, "time": 1566584280, "open": 1.11305, "close": 1.11285, "high": 1.11307, "low": 1.11282, "asset": "EURUSD"}, {"symbol_id": 1, "time": 1566584340, "open": 1.11283, "close": 1.11281, "high": 1.11293, "low": 1.11271, "asset": "EURUSD"}, {"symbol_id": 1, "time": 1566584400, "open": 1.11281, "close": 1.11288, "high": 1.11292, "low": 1.11279, "asset": "EURUSD"}, {"symbol_id": 1, "time": 1566584460, "open": 1.11288, "close": 1.11293, "high": 1.11301, "low": 1.11287, "asset": "EURUSD"}, {"symbol_id": 1, "time": 1566584520, "open": 1.11292, "close": 1.11288, "high": 1.11298, "low": 1.11282, "asset": "EURUSD"}, {"symbol_id": 1, "time": 1566584580, "open": 1.11289, "close": 1.11308, "high": 1.11309, "low": 1.11288, "asset": "EURUSD"}, {"symbol_id": 1, "time": 1566584640, "open": 1.11308, "close": 1.11312, "high": 1.11317, "low": 1.11303, "asset": "EURUSD"}, {"symbol_id": 1, "time": 1566584700, "open": 1.11312, "close": 1.11311, "high": 1.11314, "low": 1.113, "asset": "EURUSD"}, {"symbol_id": 1, "time": 1566584760, "open": 1.11312, "close": 1.11327, "high": 1.11333, "low": 1.11312, "asset": "EURUSD"}]