[{"symbol_id": 1, "time": 1695347580, "open": 1.06603, "close": 1.06602, "high": 1.06604, "low": 1.06602, "asset": "EURUSD"}, {"symbol_id": 1, "time": 1695347640, "open": 1.06602, "close": 1.06599, "high": 1.06603, "low": 1.06595, "asset": "EURUSD"}, {"symbol_id": 1, "time": 1695347700, "open": 1.06599, "close": 1.06604, "high": 1.06604, "low": 1.06598, "asset": "EURUSD"}, {"symbol_id": 1, "time": 1695347760, "open": 1.06604, "close": 1.06603, "high": 1.06604, "low": 1.06602, "asset": "EURUSD"}, {"symbol_id": 1, "time": 1695347820, "open": 1.06603, "close": 1.06597, "high": 1.06603, "low": 1.06597, "asset": "EURUSD"}, {"symbol_id": 1, "time": 1695347880, "open": 1.06597, "close": 1.06605, "high": 1.06605, "low": 1.06597, "asset": "EURUSD"}, {"symbol_id": 1, "time": 1695347940, "open": 1.06605, "close": 1.06598, "high": 1.06605, "low": 1.06598, "asset": "EURUSD"}, {"symbol_id": 1, "time": 1695348000, "open": 1.06598, "close": 1.06609, "high": 1.06623, "low": 1.06598, "asset": "EURUSD"}, {"symbol_id": 1, "time": 1695348060, "open": 1.06608, "close": 1.06607, "high": 1.06608, "low": 1.06603, "asset": "EURUSD"}, {"symbol_id": 1, "time": 1695348120, "open": 1.06605, "close": 1.06584, "high": 1.06608, "low": 1.06577, "asset": "EURUSD"}, {"symbol_id": 1, "time": 1695348180, "open": 1.06584, "close": 1.06603, "high": 1.06608, "low": 1.06584, "asset": "EURUSD"}, {"symbol_id": 1, "time": 1695348240, "open": 1.06602, "close": 1.06602, "high": 1.06606, "low": 1.06601, "asset": "EURUSD"}, {"symbol_id": 1, "time": 1695348300, "open": 1.06602, "close": 1.06591, "high": 1.06603, "low": 1.0659, "asset": "EURUSD"}, {"symbol_id": 1, "time": 1695348360, "open": 1.06587, "close": 1.06587, "high": 1.06588, "low": 1.06582, "asset": "EURUSD"}, {"symbol_id": 1, "time": 1695348420, "open": 1.06587, "close": 1.06571, "high": 1.06588, "low": 1.06571, "asset": "EURUSD"}, {"symbol_id": 1, "time": 1695348480, "open": 1.06571, "close": 1.0657, "high": 1.06578, "low": 1.06569, "asset": "EURUSD"}, {"symbol_id": 1, "time": 1695348540, "open": 1.0657, "close": 1.06574, "high": 1.06578, "low": 1.06567, "asset": "EURUSD"}, {"symbol_id": 1, "time": 1695348600, "open": 1.06574, "close": 1.06572, "high": 1.06574, "low": 1.06563, "asset": "EURUSD"}, {"symbol_id": 1, "time": 1695348660, "open": 1.06572, "close": 1.06563, "high": 1.06573, "low": 1.06561, "asset": "EURUSD"}, {"symbol_id": 1, "time": 1695348720, "open": 1.06563, "close": 1.06555, "high": 1.06564, "low": 1.06553, "asset": "EURUSD"}, {"symbol_id": 1, "time": 1695348780, "open": 1.06559, "close": 1.06549, "high": 1.06559, "low": 1.06549, "asset": "EURUSD"}, {"symbol_id": 1, "time": 1695348840, "open": 1.06549, "close": 1.06559, "high": 1.06561, "low": 1.06549, "asset": "EURUSD"}, {"symbol_id": 1, "time": 1695348900, "open": 1.06559, "close": 1.0656, "high": 1.06565, "low": 1.06558, "asset": "EURUSD"}, {"symbol_id": 1, "time": 1695348960, "open": 1.0656, "close": 1.06561, "high": 1.06565, "low": 1.0656, "asset": "EURUSD"}, {"symbol_id": 1, "time": 1695349020, "open": 1.06563, "close": 1.06552, "high": 1.06564, "low": 1.06546, "asset": "EURUSD"}, {"symbol_id": 1, "time": 1695349080, "open": 1.06552, "close": 1.0655, "high": 1.06556, "low": 1.06546, "asset": "EURUSD"}, {"symbol_id": 1, "time": 1695349140, "open": 1.0655, "close": 1.06555, "high": 1.06555, "low": 1.06549, "asset": "EURUSD"}, {"symbol_id": 1, "time": 1695349200, "open": 1.06557, "close": 1.06559, "high": 1.0656, "low": 1.06557, "asset": "EURUSD"}, {"symbol_id": 1, "time": 1695349260, "open": 1.06559, "close": 1.06563, "high": 1.06565, "low": 1.06559, "asset": "EURUSD"}, {"symbol_id": 1, "time": 1695349320, "open": 1.06563, "close": 1.06563, "high": 1.06573, "low": 1.06563, "asset": "EURUSD"}, {"symbol_id": 1, "time": 1695349380, "open": 1.06563, "close": 1.06554, "high": 1.06564, "low": 1.06554, "asset": "EURUSD"}, {"symbol_id": 1, "time": 1695349440, "open": 1.06554, "close": 1.0655, "high": 1.06554, "low": 1.06547, "asset": "EURUSD"}, {"symbol_id": 1, "time": 1695349500, "open": 1.0655, "close": 1.06544, "high": 1.06551, "low": 1.06543, "asset": "EURUSD"}, {"symbol_id": 1, "time": 1695349560, "open": 1.06544, "close": 1.06543, "high": 1.06549, "low": 1.06539, "asset": "EURUSD"}, {"symbol_id": 1, "time": 1695349620, "open": 1.06543, "close": 1.06544, "high": 1.06545, "low": 1.06543, "asset": "EURUSD"}, {"symbol_id": 1, "time": 1695349680, "open": 1.06544, "close": 1.06549, "high": 1.06549, "low": 1.06539, "asset": "EURUSD"}, {"symbol_id": 1, "time": 1695349740, "open": 1.06549, "close": 1.0655, "high": 1.06552, "low": 1.06547, "asset": "EURUSD"}, {"symbol_id": 1, "time": 1695349800, "open": 1.0655, "close": 1.06541, "high": 1.0655, "low": 1.06537, "asset": "EURUSD"}, {"symbol_id": 1, "time": 1695349860, "open": 1.06538, "close": 1.06537, "high": 1.06542, "low": 1.06531, "asset": "EURUSD"}, {"symbol_id": 1, "time": 1695349920, "open": 1.06537, "close": 1.0654, "high": 1.0654, "low": 1.06535, "asset": "EURUSD"}, {"symbol_id": 1, "time": 1695349980, "open": 1.06542, "close": 1.06542, "high": 1.06544, "low": 1.0653, "asset": "EURUSD"}, {"symbol_id": 1, "time": 1695350040, "open": 1.06542, "close": 1.06547, "high": 1.06551, "low": 1.06542, "asset": "EURUSD"}, {"symbol_id": 1, "time": 1695350100, "open": 1.06547, "close": 1.06536, "high": 1.06549, "low": 1.06532, "asset": "EURUSD"}, {"symbol_id": 1, "time": 1695350160, "open": 1.06536, "close": 1.0655, "high": 1.06552, "low": 1.06536, "asset": "EURUSD"}, {"symbol_id": 1, "time": 1695350220, "open": 1.06548, "close": 1.0655, "high": 1.06556, "low": 1.06545, "asset": "EURUSD"}, {"symbol_id": 1, "time": 1695350280, "open": 1.06548, "close": 1.06551, "high": 1.06553, "low": 1.06548, "asset": "EURUSD"}, {"symbol_id": 1, "time": 1695350340, "open": 1.06552, "close": 1.06554, "high": 1.06557, "low": 1.06551, "asset": "EURUSD"}, {"symbol_id": 1, "time": 1695350400, "open": 1.06554, "close": 1.06546, "high": 1.06555, "low": 1.06543, "asset": "EURUSD"}, {"symbol_id": 1, "time": 1695350460, "open": 1.06546, "close": 1.06548, "high": 1.06548, "low": 1.06541, "asset": "EURUSD"}, {"symbol_id": 1, "time": 1695350520, "open": 1.06548, "close": 1.06546, "high": 1.06548, "low": 1.06543, "asset": "EURUSD"}, {"symbol_id": 1, "time": 1695350580, "open": 1.06546, "close": 1.06548, "high": 1.06552, "low": 1.06542, "asset": "EURUSD"}, {"symbol_id": 1, "time": 1695350640, "open": 1.06548, "close": 1.06567, "high": 1.06567, "low": 1.06547, "asset": "EURUSD"}, {"symbol_id": 1, "time": 1695350700, "open": 1.06567, "close": 1.06569, "high": 1.06573, "low": 1.06567, "asset": "EURUSD"}, {"symbol_id": 1, "time": 1695350760, "open": 1.06569, "close": 1.06562, "high": 1.06573, "low": 1.06562, "asset": "EURUSD"}, {"symbol_id": 1, "time": 1695350820, "open": 1.06562, "close": 1.06562, "high": 1.06563, "low": 1.06557, "asset": "EURUSD"}, {"symbol_id": 1, "time": 1695350880, "open": 1.06562, "close": 1.06562, "high": 1.06564, "low": 1.06559, "asset": "EURUSD"}, {"symbol_id": 1, "time": 1695350940, "open": 1.06562, "close": 1.06569, "high": 1.06569, "low": 1.06561, "asset": "EURUSD"}, {"symbol_id": 1, "time": 1695351000, "open": 1.06569, "close": 1.06571, "high": 1.06574, "low": 1.06567, "asset": "EURUSD"}, {"symbol_id": 1, "time": 1695351060, "open": 1.06572, "close": 1.06564, "high": 1.06572, "low": 1.06564, "asset": "EURUSD"}, {"symbol_id": 1, "time": 1695351120, "open": 1.06564, "close": 1.06573, "high": 1.06573, "low": 1.06563, "asset": "EURUSD"}, {"symbol_id": 1, "time": 1695351180, "open": 1.06573, "close": 1.06582, "high": 1.06582, "low": 1.06572, "asset": "EURUSD"}, {"symbol_id": 1, "time": 1695351240, "open": 1.06582, "close": 1.06592, "high": 1.06602, "low": 1.06579, "asset": "EURUSD"}, {"symbol_id": 1, "time": 1695351300, "open": 1.06591, "close": 1.06582, "high": 1.06591, "low": 1.0658, "asset": "EURUSD"}, {"symbol_id": 1, "time": 1695351360, "open": 1.06582, "close": 1.06585, "high": 1.06587, "low": 1.06582, "asset": "EURUSD"}, {"symbol_id": 1, "time": 1695351420, "open": 1.06585, "close": 1.06583, "high": 1.06587, "low": 1.0658, "asset": "EURUSD"}, {"symbol_id": 1, "time": 1695351480, "open": 1.06583, "close": 1.06577, "high": 1.06584, "low": 1.06576, "asset": "EURUSD"}, {"symbol_id": 1, "time": 1695351540, "open": 1.06577, "close": 1.06572, "high": 1.06577, "low": 1.06569, "asset": "EURUSD"}, {"symbol_id": 1, "time": 1695351600, "open": 1.06573, "close": 1.06574, "high": 1.06574, "low": 1.06567, "asset": "EURUSD"}, {"symbol_id": 1, "time": 1695351660, "open": 1.06574, "close": 1.06555, "high": 1.06574, "low": 1.06555, "asset": "EURUSD"}, {"symbol_id": 1, "time": 1695351720, "open": 1.06555, "close": 1.0655, "high": 1.06555, "low": 1.06545, "asset": "EURUSD"}, {"symbol_id": 1, "time": 1695351780, "open": 1.0655, "close": 1.06542, "high": 1.06553, "low": 1.0654, "asset": "EURUSD"}, {"symbol_id": 1, "time": 1695351840, "open": 1.06542, "close": 1.06526, "high": 1.06542, "low": 1.06526, "asset": "EURUSD"}, {"symbol_id": 1, "time": 1695351900, "open": 1.06526, "close": 1.06522, "high": 1.06527, "low": 1.0651, "asset": "EURUSD"}, {"symbol_id": 1, "time": 1695351960, "open": 1.06522, "close": 1.06515, "high": 1.06528, "low": 1.06514, "asset": "EURUSD"}, {"symbol_id": 1, "time": 1695352020, "open": 1.06515, "close": 1.06521, "high": 1.06521, "low": 1.06512, "asset": "EURUSD"}, {"symbol_id": 1, "time": 1695352080, "open": 1.06521, "close": 1.06532, "high": 1.06532, "low": 1.06521, "asset": "EURUSD"}, {"symbol_id": 1, "time": 1695352140, "open": 1.06532, "close": 1.06537, "high": 1.06537, "low": 1.0653, "asset": "EURUSD"}, {"symbol_id": 1, "time": 1695352200, "open": 1.06537, "close": 1.06533, "high": 1.06539, "low": 1.06532, "asset": "EURUSD"}, {"symbol_id": 1, "time": 1695352260, "open": 1.06533, "close": 1.06488, "high": 1.06534, "low": 1.0647, "asset": "EURUSD"}, {"symbol_id": 1, "time": 1695352320, "open": 1.06488, "close": 1.06463, "high": 1.06493, "low": 1.06461, "asset": "EURUSD"}, {"symbol_id": 1, "time": 1695352380, "open": 1.06463, "close": 1.06478, "high": 1.06478, "low": 1.06461, "asset": "EURUSD"}, {"symbol_id": 1, "time": 1695352440, "open": 1.06478, "close": 1.06487, "high": 1.06488, "low": 1.06476, "asset": "EURUSD"}, {"symbol_id": 1, "time": 1695352500, "open": 1.06487, "close": 1.06467, "high": 1.06498, "low": 1.06467, "asset": "EURUSD"}, {"symbol_id": 1, "time": 1695352560, "open": 1.06467, "close": 1.06478, "high": 1.0648, "low": 1.06467, "asset": "EURUSD"}, {"symbol_id": 1, "time": 1695352620, "open": 1.06478, "close": 1.06473, "high": 1.06478, "low": 1.06464, "asset": "EURUSD"}, {"symbol_id": 1, "time": 1695352680, "open": 1.06472, "close": 1.06473, "high": 1.06475, "low": 1.06472, "asset": "EURUSD"}, {"symbol_id": 1, "time": 1695352740, "open": 1.06473, "close": 1.0647, "high": 1.06477, "low": 1.06468, "asset": "EURUSD"}, {"symbol_id": 1, "time": 1695352800, "open": 1.0647, "close": 1.06465, "high": 1.0647, "low": 1.0646, "asset": "EURUSD"}, {"symbol_id": 1, "time": 1695352860, "open": 1.06465, "close": 1.06465, "high": 1.06471, "low": 1.06454, "asset": "EURUSD"}, {"symbol_id": 1, "time": 1695352920, "open": 1.06465, "close": 1.06462, "high": 1.06467, "low": 1.06462, "asset": "EURUSD"}, {"symbol_id": 1, "time": 1695352980, "open": 1.06462, "close": 1.0646, "high": 1.06466, "low": 1.0646, "asset": "EURUSD"}, {"symbol_id": 1, "time": 1695353040, "open": 1.0646, "close": 1.06461, "high": 1.06463, "low": 1.06455, "asset": "EURUSD"}, {"symbol_id": 1, "time": 1695353100, "open": 1.06462, "close": 1.06465, "high": 1.06465, "low": 1.06461, "asset": "EURUSD"}, {"symbol_id": 1, "time": 1695353160, "open": 1.06465, "close": 1.0646, "high": 1.06466, "low": 1.0646, "asset": "EURUSD"}, {"symbol_id": 1, "time": 1695353220, "open": 1.0646, "close": 1.06441, "high": 1.0646, "low": 1.06439, "asset": "EURUSD"}, {"symbol_id": 1, "time": 1695353280, "open": 1.06439, "close": 1.06455, "high": 1.06455, "low": 1.06439, "asset": "EURUSD"}, {"symbol_id": 1, "time": 1695353340, "open": 1.06456, "close": 1.06459, "high": 1.06463, "low": 1.06455, "asset": "EURUSD"}, {"symbol_id": 1, "time": 1695353400, "open": 1.06458, "close": 1.06454, "high": 1.06458, "low": 1.06447, "asset": "EURUSD"}, {"symbol_id": 1, "time": 1695353460, "open": 1.06454, "close": 1.06446, "high": 1.06458, "low": 1.06446, "asset": "EURUSD"}, {"symbol_id": 1, "time": 1695353520, "open": 1.06444, "close": 1.06431, "high": 1.06444, "low": 1.06429, "asset": "EURUSD"}, {"symbol_id": 1, "time": 1695353580, "open": 1.06431, "close": 1.06414, "high": 1.06434, "low": 1.06413, "asset": "EURUSD"}, {"symbol_id": 1, "time": 1695353640, "open": 1.06414, "close": 1.06426, "high": 1.06426, "low": 1.06414, "asset": "EURUSD"}, {"symbol_id": 1, "time": 1695353700, "open": 1.06423, "close": 1.06433, "high": 1.06433, "low": 1.06423, "asset": "EURUSD"}, {"symbol_id": 1, "time": 1695353760, "open": 1.06433, "close": 1.06424, "high": 1.06433, "low": 1.06423, "asset": "EURUSD"}, {"symbol_id": 1, "time": 1695353820, "open": 1.06423, "close": 1.06414, "high": 1.06423, "low": 1.06413, "asset": "EURUSD"}, {"symbol_id": 1, "time": 1695353880, "open": 1.06414, "close": 1.06411, "high": 1.06418, "low": 1.06411, "asset": "EURUSD"}, {"symbol_id": 1, "time": 1695353940, "open": 1.06409, "close": 1.06414, "high": 1.06415, "low": 1.06409, "asset": "EURUSD"}, {"symbol_id": 1, "time": 1695354000, "open": 1.06414, "close": 1.06413, "high": 1.06421, "low": 1.0641, "asset": "EURUSD"}, {"symbol_id": 1, "time": 1695354060, "open": 1.06413, "close": 1.06408, "high": 1.0642, "low": 1.06407, "asset": "EURUSD"}, {"symbol_id": 1, "time": 1695354120, "open": 1.06408, "close": 1.06413, "high": 1.06415, "low": 1.06408, "asset": "EURUSD"}, {"symbol_id": 1, "time": 1695354180, "open": 1.06413, "close": 1.06409, "high": 1.06418, "low": 1.06407, "asset": "EURUSD"}, {"symbol_id": 1, "time": 1695354240, "open": 1.06409, "close": 1.06409, "high": 1.06413, "low": 1.06409, "asset": "EURUSD"}, {"symbol_id": 1, "time": 1695354300, "open": 1.06409, "close": 1.06418, "high": 1.06418, "low": 1.06409, "asset": "EURUSD"}, {"symbol_id": 1, "time": 1695354360, "open": 1.06418, "close": 1.06417, "high": 1.06419, "low": 1.06414, "asset": "EURUSD"}, {"symbol_id": 1, "time": 1695354420, "open": 1.06417, "close": 1.06419, "high": 1.06419, "low": 1.06416, "asset": "EURUSD"}, {"symbol_id": 1, "time": 1695354480, "open": 1.06419, "close": 1.0642, "high": 1.06422, "low": 1.06417, "asset": "EURUSD"}, {"symbol_id": 1, "time": 1695354540, "open": 1.0642, "close": 1.06422, "high": 1.06425, "low": 1.06418, "asset": "EURUSD"}, {"symbol_id": 1, "time": 1695354600, "open": 1.06422, "close": 1.06418, "high": 1.06423, "low": 1.06417, "asset": "EURUSD"}, {"symbol_id": 1, "time": 1695354660, "open": 1.06418, "close": 1.0641, "high": 1.06423, "low": 1.0641, "asset": "EURUSD"}, {"symbol_id": 1, "time": 1695354720, "open": 1.06411, "close": 1.06414, "high": 1.06414, "low": 1.06408, "asset": "EURUSD"}, {"symbol_id": 1, "time": 1695354780, "open": 1.06415, "close": 1.06414, "high": 1.06418, "low": 1.06406, "asset": "EURUSD"}, {"symbol_id": 1, "time": 1695354840, "open": 1.06414, "close": 1.06413, "high": 1.06416, "low": 1.0641, "asset": "EURUSD"}, {"symbol_id": 1, "time": 1695354900, "open": 1.06413, "close": 1.06418, "high": 1.06419, "low": 1.06413, "asset": "EURUSD"}, {"symbol_id": 1, "time": 1695354960, "open": 1.06418, "close": 1.06416, "high": 1.06418, "low": 1.06414, "asset": "EURUSD"}, {"symbol_id": 1, "time": 1695355020, "open": 1.06419, "close": 1.06441, "high": 1.06441, "low": 1.06417, "asset": "EURUSD"}, {"symbol_id": 1, "time": 1695355080, "open": 1.06441, "close": 1.06437, "high": 1.06441, "low": 1.06432, "asset": "EURUSD"}, {"symbol_id": 1, "time": 1695355140, "open": 1.06437, "close": 1.06429, "high": 1.06439, "low": 1.06428, "asset": "EURUSD"}, {"symbol_id": 1, "time": 1695355200, "open": 1.06429, "close": 1.06436, "high": 1.06438, "low": 1.06429, "asset": "EURUSD"}, {"symbol_id": 1, "time": 1695355260, "open": 1.06437, "close": 1.06433, "high": 1.0644, "low": 1.06433, "asset": "EURUSD"}, {"symbol_id": 1, "time": 1695355320, "open": 1.06433, "close": 1.06437, "high": 1.0644, "low": 1.06432, "asset": "EURUSD"}, {"symbol_id": 1, "time": 1695355380, "open": 1.06437, "close": 1.06435, "high": 1.06439, "low": 1.06434, "asset": "EURUSD"}, {"symbol_id": 1, "time": 1695355440, "open": 1.06435, "close": 1.06436, "high": 1.06438, "low": 1.0643, "asset": "EURUSD"}, {"symbol_id": 1, "time": 1695355500, "open": 1.06436, "close": 1.06439, "high": 1.06439, "low": 1.06432, "asset": "EURUSD"}, {"symbol_id": 1, "time": 1695355560, "open": 1.06439, "close": 1.06441, "high": 1.06441, "low": 1.06433, "asset": "EURUSD"}, {"symbol_id": 1, "time": 1695355620, "open": 1.06441, "close": 1.06449, "high": 1.06449, "low": 1.06421, "asset": "EURUSD"}, {"symbol_id": 1, "time": 1695355680, "open": 1.06447, "close": 1.06458, "high": 1.06459, "low": 1.06447, "asset": "EURUSD"}, {"symbol_id": 1, "time": 1695355740, "open": 1.06458, "close": 1.06459, "high": 1.06459, "low": 1.06457, "asset": "EURUSD"}, {"symbol_id": 1, "time": 1695355800, "open": 1.06459, "close": 1.06451, "high": 1.06459, "low": 1.0645, "asset": "EURUSD"}, {"symbol_id": 1, "time": 1695355860, "open": 1.06451, "close": 1.06457, "high": 1.06457, "low": 1.06449, "asset": "EURUSD"}, {"symbol_id": 1, "time": 1695355920, "open": 1.06457, "close": 1.06468, "high": 1.06468, "low": 1.06457, "asset": "EURUSD"}, {"symbol_id": 1, "time": 1695355980, "open": 1.06468, "close": 1.06482, "high": 1.06486, "low": 1.06468, "asset": "EURUSD"}, {"symbol_id": 1, "time": 1695356040, "open": 1.06481, "close": 1.06479, "high": 1.06481, "low": 1.06473, "asset": "EURUSD"}, {"symbol_id": 1, "time": 1695356100, "open": 1.06479, "close": 1.06491, "high": 1.06491, "low": 1.06475, "asset": "EURUSD"}, {"symbol_id": 1, "time": 1695356160, "open": 1.06491, "close": 1.06493, "high": 1.06493, "low": 1.06486, "asset": "EURUSD"}, {"symbol_id": 1, "time": 1695356220, "open": 1.06493, "close": 1.0649, "high": 1.06494, "low": 1.06488, "asset": "EURUSD"}, {"symbol_id": 1, "time": 1695356280, "open": 1.0649, "close": 1.06488, "high": 1.06503, "low": 1.06488, "asset": "EURUSD"}, {"symbol_id": 1, "time": 1695356340, "open": 1.06488, "close": 1.06488, "high": 1.06491, "low": 1.06483, "asset": "EURUSD"}, {"symbol_id": 1, "time": 1695356400, "open": 1.06486, "close": 1.06488, "high": 1.06492, "low": 1.06485, "asset": "EURUSD"}, {"symbol_id": 1, "time": 1695356460, "open": 1.06488, "close": 1.06487, "high": 1.06488, "low": 1.06481, "asset": "EURUSD"}, {"symbol_id": 1, "time": 1695356520, "open": 1.06486, "close": 1.06479, "high": 1.0649, "low": 1.06479, "asset": "EURUSD"}]